cokodo_agent/__init__.py
cokodo_agent/__main__.py
cokodo_agent/cli.py
cokodo_agent/config.py
cokodo_agent/generator.py
cokodo_agent/linter.py
cokodo_agent/prompts.py
cokodo_agent/sync.py
cokodo_agent/bundled/agent/manifest.json
cokodo_agent/bundled/agent/start-here.md
cokodo_agent/bundled/agent/adapters/ci/github-actions.template.yml
cokodo_agent/bundled/agent/adapters/ci/pre-commit-config.template.yaml
cokodo_agent/bundled/agent/adapters/ci/readme.md
cokodo_agent/bundled/agent/adapters/claude/adapt_for_claude.py
cokodo_agent/bundled/agent/adapters/claude/instructions.template.md
cokodo_agent/bundled/agent/adapters/cursor/rules.template.md
cokodo_agent/bundled/agent/adapters/github-copilot/instructions.template.md
cokodo_agent/bundled/agent/adapters/google-antigravity/adapt_for_antigravity.py
cokodo_agent/bundled/agent/adapters/google-antigravity/instructions.template.md
cokodo_agent/bundled/agent/core/conventions.md
cokodo_agent/bundled/agent/core/core-rules.md
cokodo_agent/bundled/agent/core/examples.md
cokodo_agent/bundled/agent/core/instructions.md
cokodo_agent/bundled/agent/core/security.md
cokodo_agent/bundled/agent/core/stack-specs/git.md
cokodo_agent/bundled/agent/core/stack-specs/python.md
cokodo_agent/bundled/agent/core/stack-specs/qt.md
cokodo_agent/bundled/agent/core/stack-specs/rust.md
cokodo_agent/bundled/agent/core/workflows/ai-boundaries.md
cokodo_agent/bundled/agent/core/workflows/bug-prevention.md
cokodo_agent/bundled/agent/core/workflows/design-principles.md
cokodo_agent/bundled/agent/core/workflows/documentation.md
cokodo_agent/bundled/agent/core/workflows/pre-task-checklist.md
cokodo_agent/bundled/agent/core/workflows/quality-assurance.md
cokodo_agent/bundled/agent/core/workflows/review-process.md
cokodo_agent/bundled/agent/core/workflows/testing.md
cokodo_agent/bundled/agent/meta/adr-archive.md
cokodo_agent/bundled/agent/meta/agent-protocol-rules.md
cokodo_agent/bundled/agent/meta/protocol-adr.md
cokodo_agent/bundled/agent/project/commands.md
cokodo_agent-1.3.0.dist-info/METADATA
cokodo_agent-1.3.0.dist-info/WHEEL
cokodo_agent-1.3.0.dist-info/entry_points.txt
cokodo_agent-1.3.0.dist-info/RECORD
