Metadata-Version: 2.4
Name: cokodo-agent
Version: 1.3.0
Summary: AI Agent Collaboration Protocol Generator - Create standardized .agent protocol for your projects
Project-URL: Homepage, https://github.com/dinwind/agent_protocol
Project-URL: Repository, https://github.com/dinwind/agent_protocol
Project-URL: Issues, https://github.com/dinwind/agent_protocol/issues
Author: dinwind
License-Expression: MIT
Keywords: agent,ai,claude,cokodo,copilot,cursor,generator,protocol
Classifier: Development Status :: 4 - Beta
Classifier: Environment :: Console
Classifier: Intended Audience :: Developers
Classifier: License :: OSI Approved :: MIT License
Classifier: Operating System :: OS Independent
Classifier: Programming Language :: Python :: 3
Classifier: Programming Language :: Python :: 3.9
Classifier: Programming Language :: Python :: 3.10
Classifier: Programming Language :: Python :: 3.11
Classifier: Programming Language :: Python :: 3.12
Classifier: Topic :: Software Development :: Code Generators
Requires-Python: >=3.9
Requires-Dist: httpx>=0.25.0
Requires-Dist: jinja2>=3.1.0
Requires-Dist: questionary>=2.0.0
Requires-Dist: rich>=13.0.0
Requires-Dist: typer>=0.9.0
Provides-Extra: dev
Requires-Dist: black>=24.0.0; extra == 'dev'
Requires-Dist: mypy>=1.8.0; extra == 'dev'
Requires-Dist: pytest-cov>=4.0.0; extra == 'dev'
Requires-Dist: pytest>=7.0.0; extra == 'dev'
Requires-Dist: ruff>=0.2.0; extra == 'dev'
